MANIFEST.in
Makefile
README
setup.py
test/__init__.py
test/__init__.pyc
test/test_cors.py
test/test_example.py
test/__pycache__/test_cors.cpython-27-PYTEST.pyc
test/__pycache__/test_example.cpython-27-PYTEST.pyc
tiddlywebplugins/__init__.py
tiddlywebplugins/cors.py
tiddlywebplugins.cors.egg-info/PKG-INFO
tiddlywebplugins.cors.egg-info/SOURCES.txt
tiddlywebplugins.cors.egg-info/dependency_links.txt
tiddlywebplugins.cors.egg-info/namespace_packages.txt
tiddlywebplugins.cors.egg-info/not-zip-safe
tiddlywebplugins.cors.egg-info/requires.txt
tiddlywebplugins.cors.egg-info/top_level.txt