Metadata-Version: 1.0
Name: tiddlywebplugins.cors
Version: 0.3
Summary: CORS preflight support for TiddlyWeb
Home-page: http://pypi.python.org/pypi/tiddlywebplugins.cors
Author: Chris Dent
Author-email: cdent@peermore.com
License: UNKNOWN
Platform: Posix; MacOS X; Windows
